MANIFEST.in
README.rst
setup.py
spotinst_troposphere/__init__.py
spotinst_troposphere/aws_elastigroup.py
spotinst_troposphere/aws_elastigroup_usage.py
spotinst_troposphere/beanstalk_elastigroup.py
spotinst_troposphere/beanstalk_elastigroup_usage.py
spotinst_troposphere.egg-info/PKG-INFO
spotinst_troposphere.egg-info/SOURCES.txt
spotinst_troposphere.egg-info/dependency_links.txt
spotinst_troposphere.egg-info/requires.txt
spotinst_troposphere.egg-info/top_level.txt