Metadata-Version: 1.1
Name: spotinst-troposphere
Version: 1.0.2
Summary: A Troposphere custom resource for Spotinst elastigroup
Home-page: https://github.com/spotinst/spotinst-troposphere
Author: Spotinst
Author-email: service@spotinst.com
License: MIT
Keywords: spotinst spot instances aws ec2 cloud infrastructure development elastigroup troposphere
Platform: UNKNOWN
Classifier: Development Status :: 3 - Alpha
Classifier: Intended Audience :: Developers
Classifier: Topic :: Software Development :: Libraries :: Python Modules
Classifier: License :: OSI Approved :: MIT License
Classifier: Programming Language :: Python :: 2.7
